{
  "id": "alarm_clock",
  "name": "Alarm Clock",
  "description": "Can be recycled into crafting materials.",
  "type": "Recyclable",
  "rarity": "Rare",
  "value": 1000,
  "weight": 2,
  "stack_size": 3,
  "image_location": "https://raw.githubusercontent.com/ArcInformer/ArcInformer_Assets/refs/heads/main/Game%20Assets/Items/alarm_clock.png",
  "ingame_image": "https://raw.githubusercontent.com/ArcInformer/ArcInformer_Assets/refs/heads/main/Game%20Assets/Items_Ingame/alarm_clock.png",
  "found_in": "Residential",
  "sources": ["Scavenging"],
  "recycles_into": {
    "plastic_parts": 6,
    "processor": 1
  },
  "salvages_into": {
    "processor": 1
  },
  "last_updated": "Jan 22, 2026"
}