{
  "id": "renegade_iv",
  "name": "Renegade IV",
  "description": "Lever-action battle rifle with high damage output, accuracy, and headshot damage.",
  "type": "Battle Rifle",
  "rarity": "Rare",
  "value": 17000,
  "weight": 10,
  "stack_size": 0,
  "image_location": "https://raw.githubusercontent.com/ArcInformer/ArcInformer_Assets/refs/heads/main/Game%20AssetsItems/renegade_iv.png",
  "ingame_image": "https://raw.githubusercontent.com/ArcInformer/ArcInformer_Assets/refs/heads/main/Game%20AssetsItems_Ingame/renegade_iv.png",
  "craft_bench": "bench_gunsmith",
  "variants": [
    "renegade_i",
    "renegade_ii",
    "renegade_iii"
  ],
  "matching_blueprint": [],
  "compatible_with": [],
  "sources": [],
  "item_data": {
    "Ammo Type": "Medium Ammo",
    "ARC Armor Penetration": "Moderate",
    "Durability": "130/130",
    "Firing Mode": "Lever-Action",
    "Increased Fire Rate": "75%",
    "Magazine Size": 8,
    "Reduced Dispersion Recovery Time": "50%"
  },
  "crafting_requirements": {},
  "bench_requirements": {},
  "repair_cost": {},
  "recycles_into": {
    "advanced_mechanical_components": 3,
    "medium_gun_parts": 3
  },
  "salvages_into": {
    "medium_gun_parts": 3
  },
  "last_updated": "Jan 23, 2026",
  "agility": 55.8,
  "damage": 35,
  "fireRate": 21,
  "range": 68.8,
  "stability": 85.7,
  "stealth": 16
}