{
    "id":  "vita_shot",
    "name":  "Vita Shot",
    "description":  "A medical item that restores a large amount of health.",
    "type":  "Quick Use",
    "rarity":  "Rare",
    "value":  2200,
    "weight":  0.4,
    "stack_size":  3,
    "recycles_into":  {
        "chemicals":  4,
        "syringe":  1
    },
    "image_location":  "https://raw.githubusercontent.com/ArcInformer/ArcInformer_Assets/refs/heads/main/Game%20Assets/Items/vita_shot.png",
    "in_game_image_location":  "https://raw.githubusercontent.com/ArcInformer/ArcInformer_Assets/refs/heads/main/Game%20Assets/Items_Ingame/vita_shot.png",
    "last_updated": "15/01/2026"
}
